<?xml version="1.0" encoding="utf-8"?>
<eml:eml xmlns:eml="eml://ecoinformatics.org/eml-2.1.1" xmlns:dc="http://purl.org/dc/terms/" xmlns:xsi="http://www.w3.org/2001/XMLSchema-instance" xsi:schemaLocation="eml://ecoinformatics.org/eml-2.1.1 http://rs.gbif.org/schema/eml-gbif-profile/1.0.1/eml.xsd" packageId="92ac30c7-6a41-497a-8755-45766dea0dd6" system="https://symbiota.org" scope="system" xml:lang="eng"><dataset><alternateIdentifier>https://ecdysis.org/collections/misc/collprofiles.php?collid=73</alternateIdentifier><title xml:lang="eng">University of Arizona Insect Collection</title><creator id="b925ff4c-8eba-495c-b5ed-852c7affb2ea"><organizationName>Ecdysis</organizationName><electronicMailAddress></electronicMailAddress><onlineUrl>https://ecdysis.org/index.php</onlineUrl></creator><metadataProvider><organizationName>Ecdysis</organizationName><electronicMailAddress></electronicMailAddress><onlineUrl>https://ecdysis.org/index.php</onlineUrl></metadataProvider><pubDate>2026-06-19</pubDate><language>eng</language><abstract><para>The University of Arizona Insect Collection (UAIC) contains approximately 2 million specimens representing 35,000 species of pinned, alcohol-preserved, slide-mounted and frozen-tissue preserved arthropods mostly from the Sonoran Desert Region. Significant holdings include Coleoptera, Hemiptera, Hymenoptera, Orthoptera and Lepidoptera, but all insect groups are extensively represented. The UAIC user community is diverse, ranging from outstanding undergraduate and graduate students to highly active emeritus insect systematists. Annually, we host thousands of visitors, ranging from resident researchers to individual walk-ins, campus tour groups, and vast numbers of people seeking information on the biology of the Sonoran Desert Region.</para></abstract><contact><organizationName>University of Arizona Insect Collection</organizationName><phone></phone><electronicMailAddress>wmoore@email.arizona.edu</electronicMailAddress><onlineUrl>https://uaic.arizona.edu</onlineUrl></contact><associatedParty><individualName><surName>Moore</surName><givenName>Wendy</givenName></individualName><positionName>Curator</positionName><electronicMailAddress>wmoore@email.arizona.edu</electronicMailAddress><role>contentProvider</role></associatedParty><intellectualRights><para>To the extent possible under law, the publisher has waived all rights to these data and has dedicated them to the <ulink url="http://creativecommons.org/publicdomain/zero/1.0/"><citetitle></citetitle></ulink></para></intellectualRights></dataset><additionalMetadata><metadata><symbiota id="b925ff4c-8eba-495c-b5ed-852c7affb2ea"><dateStamp>2026-06-19T08:45:33-07:00</dateStamp><citation identifier="d9eed1f5-d661-4fc6-999d-438d88d1e346">Ecdysis - d9eed1f5-d661-4fc6-999d-438d88d1e346</citation><physical><characterEncoding>UTF-8</characterEncoding><dataFormat><externallyDefinedFormat><formatName>Darwin Core Archive</formatName></externallyDefinedFormat></dataFormat></physical><collection identifier="d6e5984e-21f9-42af-8346-229b107a8631" id="73"><alternateIdentifier>https://ecdysis.org/collections/misc/collprofiles.php?collid=73</alternateIdentifier><parentCollectionIdentifier>UA</parentCollectionIdentifier><collectionIdentifier>UAIC</collectionIdentifier><collectionName>University of Arizona Insect Collection</collectionName><resourceLogoUrl>https://ecdysis.org/content/collicon/uauaic.jpeg</resourceLogoUrl><onlineUrl>https://uaic.arizona.edu</onlineUrl><intellectualRights>http://creativecommons.org/publicdomain/zero/1.0/</intellectualRights><additionalInfo>University of Arizona Insect Collection (UA-UA)</additionalInfo><associatedParty><individualName><surName>Moore</surName><givenName>Wendy</givenName></individualName><positionName>Curator</positionName><electronicMailAddress>wmoore@email.arizona.edu</electronicMailAddress></associatedParty><abstract><para>&lt;p&gt;&lt;span style="font-family: Verdana, Geneva, sans-serif; font-size: 12px; background-color: #ffffff;"&gt;The University of Arizona Insect Collection (UAIC) contains approximately 2 million specimens representing 35,000 species of pinned, alcohol-preserved, slide-mounted and frozen-tissue preserved arthropods mostly from the Sonoran Desert Region. Significant holdings include Coleoptera, Hemiptera, Hymenoptera, Orthoptera and Lepidoptera, but all insect groups are extensively represented. The UAIC user community is diverse, ranging from outstanding undergraduate and graduate students to highly active emeritus insect systematists. Annually, we host thousands of visitors, ranging from resident researchers to individual walk-ins, campus tour groups, and vast numbers of people seeking information on the biology of the Sonoran Desert Region.&lt;/span&gt;&lt;/p&gt;</para></abstract></collection></symbiota></metadata></additionalMetadata></eml:eml>
